{
    "id": 12318,
    "citation_title": "Contributions of Zvi Griliches",
    "citation_author": [
        "James Heckman"
    ],
    "citation_publication_date": "2006-06-26",
    "issue_date": "2006-06-26",
    "revision_date": "None",
    "topics": [
        "Other",
        "History of Economic Thought",
        "Microeconomics",
        "Households and Firms",
        "Development and Growth",
        "Innovation and R&D"
    ],
    "program": [
        "Industrial Organization",
        "Economics of Education",
        "Labor Studies",
        "Productivity, Innovation, and Entrepreneurship"
    ],
    "projects": null,
    "working_groups": null,
    "abstract": "\n\nThis paper summarizes the major research contributions of Zvi Griliches.\n\n",
    "acknowledgement": "\n"
}