{
    "id": 18982,
    "cites": 37,
    "cited_by": 7,
    "reference": [
        "Anton, J., and D. A. Yao (1994): \u00c3\u00a2\u00e2\u0082\u00ac\u00c5\u0093Expropriation and Inventions: Appropriable Rents in the Absence of Property Rights,\u00c3\u00a2\u00e2\u0082\u00ac\u00c2\u009d American Economic Review, 84 (1), 190\u00c3\u00a2\u00e2\u0082\u00ac\u00e2\u0080\u009d209.",
        "Argote, L., P. Ingram, J. M. Levine, and R. L. Moreland (2000): \u00c3\u00a2\u00e2\u0082\u00ac\u00c5\u0093Knowledge Transfer in Organizations: Learning from the Experience of Others,\u00c3\u00a2\u00e2\u0082\u00ac\u00c2\u009d Organizational Behavior and Human Decision Processes, 82 (1), 1\u00c3\u00a2\u00e2\u0082\u00ac\u00e2\u0080\u009d8.",
        "Arora, A. (1995): \u00c3\u00a2\u00e2\u0082\u00ac\u00c5\u0093Licensing Tacit Knowledge: Intellectual Property Rights and the Market for Know-How,\u00c3\u00a2\u00e2\u0082\u00ac\u00c2\u009d Economics of Innovation & New Technology, 4, 41\u00c3\u00a2\u00e2\u0082\u00ac\u00e2\u0080\u009d59.",
        "Arora, A., and M. Ceccagnoli (2006): \u00c3\u00a2\u00e2\u0082\u00ac\u00c5\u0093Patent Protection, Complementary Assets and Firms\u00c3\u00a2\u00e2\u0082\u00ac\u00e2\u0084\u00a2Incentives for Technology Licensing,\u00c3\u00a2\u00e2\u0082\u00ac\u00c2\u009d Management Science, 52, 293\u00c3\u00a2\u00e2\u0082\u00ac\u00e2\u0080\u009d308.",
        "Arora, A., A. Fosfuri, and A. Gambardella (2001): Market for Technology: The Economics of Innovation and Corporate Strategy. The MIT Press.",
        "Arora, A., and A. Gambardella (1994): \u00c3\u00a2\u00e2\u0082\u00ac\u00c5\u0093Evaluating technological information and utilizing it: Scientific knowledge, technological capability and external linkages in biotechnology,\u00c3\u00a2\u00e2\u0082\u00ac\u00c2\u009d Journal of Economic Behavior and Organisation, 24 (1), 91\u00c3\u00a2\u00e2\u0082\u00ac\u00e2\u0080\u009d114.",
        "Arrow, K. (1962): \u00c3\u00a2\u00e2\u0082\u00ac\u00c5\u0093Economic Welfare and the Allocation of Resources for Invention,\u00c3\u00a2\u00e2\u0082\u00ac\u00c2\u009d in Rate and Direction of Inventive Activity. NBER and Princeton Univ. Press, Princeton, NJ.",
        "(1983): \u00c3\u00a2\u00e2\u0082\u00ac\u00c5\u0093Innovation in Large and Small Firms,\u00c3\u00a2\u00e2\u0082\u00ac\u00c2\u009d in Entrepreneurship, ed. by J. Ronen. Lexington Books, Lexington, MA.",
        "Cassiman, B., and M. Ueda (2006): \u00c3\u00a2\u00e2\u0082\u00ac\u00c5\u0093Optimal project rejection and new firm start-ups,\u00c3\u00a2\u00e2\u0082\u00ac\u00c2\u009d Management Science, 52, 262\u00c3\u00a2\u00e2\u0082\u00ac\u00e2\u0080\u009d275.",
        "Cohen, W. M., and D. A. Levinthal (1990): \u00c3\u00a2\u00e2\u0082\u00ac\u00c5\u0093Absorptive Capacity: A New Perspective on Learning and Innovation,\u00c3\u00a2\u00e2\u0082\u00ac\u00c2\u009d Administrative Science Quarterly, 35 (1), 128\u00c3\u00a2\u00e2\u0082\u00ac\u00e2\u0080\u009d152.",
        "Dykeman, D., and D. Kopko (2004): \u00c3\u00a2\u00e2\u0082\u00ac\u00c5\u0093Recording Patent License Agreements in the USPTO,\u00c3\u00a2\u00e2\u0082\u00ac\u00c2\u009d Intellectual Property Today, August, 18\u00c3\u00a2\u00e2\u0082\u00ac\u00e2\u0080\u009d19.",
        "FTC (2012): \u00c3\u00a2\u00e2\u0082\u00ac\u00c5\u0093Patent Assertion Entity Activities Workshop,\u00c3\u00a2\u00e2\u0082\u00ac\u00c2\u009d Washington DC.",
        "Galasso, A., M. Schankerman, and C. J. Serrano (2013): \u00c3\u00a2\u00e2\u0082\u00ac\u00c5\u0093Trading and Enforcing of Patent Rights,\u00c3\u00a2\u00e2\u0082\u00ac\u00c2\u009d The RAND Journal of Economics, 44 (2), Forthcoming.",
        "Gans, J., D. Hsu, and S. Stern (2002): \u00c3\u00a2\u00e2\u0082\u00ac\u00c5\u0093When Does Start-Up Innovation Spur the Gale of Creative Destruction?,\u00c3\u00a2\u00e2\u0082\u00ac\u00c2\u009d RAND Journal of Economics, 33, 571\u00c3\u00a2\u00e2\u0082\u00ac\u00e2\u0080\u009d586.",
        "Gans, J., and S. Stern (2000): \u00c3\u00a2\u00e2\u0082\u00ac\u00c5\u0093Incumbency and R&D Incentives: Licensing The Gale of Creative Destruction,\u00c3\u00a2\u00e2\u0082\u00ac\u00c2\u009d Journal of Economics & Management Strategy, 9 (4), 485\u00c3\u00a2\u00e2\u0082\u00ac\u00e2\u0080\u009d511.",
        "(2003): \u00c3\u00a2\u00e2\u0082\u00ac\u00c5\u0093The Product Market and the Market for \"Ideas\": Commercialization Strategies for Technology Entrepreneurs,\u00c3\u00a2\u00e2\u0082\u00ac\u00c2\u009d Research Policy, 32, 333\u00c3\u00a2\u00e2\u0082\u00ac\u00e2\u0080\u009d350.",
        "(2010): \u00c3\u00a2\u00e2\u0082\u00ac\u00c5\u0093Is Their a Market for Ideas?,\u00c3\u00a2\u00e2\u0082\u00ac\u00c2\u009d Industrial and Corporate Change, 19 (3), 805\u00c3\u00a2\u00e2\u0082\u00ac\u00e2\u0080\u009d837.",
        "Gans, J. S., D. Hsu, and S. Stern (2008): \u00c3\u00a2\u00e2\u0082\u00ac\u00c5\u0093The Impact of Uncertain Intellectual Property Rights on the Market for Ideas: Evidence from Patent Grant Delays,\u00c3\u00a2\u00e2\u0082\u00ac\u00c2\u009d Management Science, 54, 982\u00c3\u00a2\u00e2\u0082\u00ac\u00e2\u0080\u009d997.",
        "Hahn, R. W. (1984): \u00c3\u00a2\u00e2\u0082\u00ac\u00c5\u0093Market Power and Transferable Property Righ,\u00c3\u00a2\u00e2\u0082\u00ac\u00c2\u009d Quarterly Journal of Economics, 99 (4), 753\u00c3\u00a2\u00e2\u0082\u00ac\u00e2\u0080\u009d765.",
        "Hall, B. H., A. B. Jaffe, and M. Trajtenberg (2001): \u00c3\u00a2\u00e2\u0082\u00ac\u00c5\u0093The NBER Patent Citation Data File: Lessons, Insights and Methodological Tools,\u00c3\u00a2\u00e2\u0082\u00ac\u00c2\u009d NBER Working Paper 8498.",
        "Hellmann, T. F., and E. C. Perotti (2011): \u00c3\u00a2\u00e2\u0082\u00ac\u00c5\u0093The Circulation of Ideas in Firms and Markets,\u00c3\u00a2\u00e2\u0082\u00ac\u00c2\u009d Management Science, 57 (10), 1813\u00c3\u00a2\u00e2\u0082\u00ac\u00e2\u0080\u009d1826.",
        "Henderson, R., and I. Cockburn (1996): \u00c3\u00a2\u00e2\u0082\u00ac\u00c5\u0093Scale, Scope, and Spillovers: The Determinants of Research Productivity in Drug Discovery,\u00c3\u00a2\u00e2\u0082\u00ac\u00c2\u009d RAND Journal of Economics, 27 (1), 32\u00c3\u00a2\u00e2\u0082\u00ac\u00e2\u0080\u009d59.",
        "Holmstrom, B. (1989): \u00c3\u00a2\u00e2\u0082\u00ac\u00c5\u0093Agency Costs and Innovation,\u00c3\u00a2\u00e2\u0082\u00ac\u00c2\u009d Journal of Economic Behavior and Organization, 12 (3), 305\u00c3\u00a2\u00e2\u0082\u00ac\u00e2\u0080\u009d327.",
        "Lamoreaux, N., and K. Sokoloff (1997): \u00c3\u00a2\u00e2\u0082\u00ac\u00c5\u0093Inventors, Firms, and the Market for Technology: U.S. Manufacturing in the Late Nineteenth and Early Twentieth Centuries,\u00c3\u00a2\u00e2\u0082\u00ac\u00c2\u009d NBER Working Paper H0098.",
        "(1999): \u00c3\u00a2\u00e2\u0082\u00ac\u00c5\u0093Inventive Activity and the Market for Technology in the United States, 18401920, \u00c3\u00a2\u00e2\u0082\u00ac\u00c2\u009d NBER Working Paper 7107.",
        "Lamoreaux, N. R., and K. L. Sokoloff (2001): \u00c3\u00a2\u00e2\u0082\u00ac\u00c5\u0093Market Trade in Patents and the Rise of a Class of Specialized Inventors in the 19th-Century United States,\u00c3\u00a2\u00e2\u0082\u00ac\u00c2\u009d American Economic Review P&P, 91 (2), 39\u00c3\u00a2\u00e2\u0082\u00ac\u00e2\u0080\u009d44.",
        "Lanjouw, J. O., and M. Schankerman (2004): \u00c3\u00a2\u00e2\u0082\u00ac\u00c5\u0093Protecting intellectual property rights: are small firms handicapped?,\u00c3\u00a2\u00e2\u0082\u00ac\u00c2\u009d The Journal of Law and Economics, 47 (1), 45\u00c3\u00a2\u00e2\u0082\u00ac\u00e2\u0080\u009d74.",
        "Lemley, M. A., and N. Myhrvold (2008): \u00c3\u00a2\u00e2\u0082\u00ac\u00c5\u0093How to Make a Patent Market,\u00c3\u00a2\u00e2\u0082\u00ac\u00c2\u009d Hofstra Law Review, 36, 257.",
        "Lemley, M. A., and C. Shapiro (2005): \u00c3\u00a2\u00e2\u0082\u00ac\u00c5\u0093Probabilistic Patents,\u00c3\u00a2\u00e2\u0082\u00ac\u00c2\u009d Journal of Economic Perspectives, 19 (2), 75\u00c3\u00a2\u00e2\u0082\u00ac\u00e2\u0080\u009d98.",
        "Lerner, J., and R. P. Merges (1998): \u00c3\u00a2\u00e2\u0082\u00ac\u00c5\u0093The Control of Technology Alliances: An Empirical Analysis of the Biotechnology Industry,\u00c3\u00a2\u00e2\u0082\u00ac\u00c2\u009d Journal of Industrial Economics, 46 (2), 125\u00c3\u00a2\u00e2\u0082\u00ac\u00e2\u0080\u009d156.",
        "Moser, P. (2013): \u00c3\u00a2\u00e2\u0082\u00ac\u00c5\u0093Patents and Innovation \u00c3\u008b\u00c2\u009d U Evidence from Economic History,\u00c3\u00a2\u00e2\u0082\u00ac\u00c2\u009d The Journal of Economic Perspectives, 27 (1), 23\u00c3\u00a2\u00e2\u0082\u00ac\u00e2\u0080\u009d44.",
        "Nelson, R. R. (1959): \u00c3\u00a2\u00e2\u0082\u00ac\u00c5\u0093The Simple Economics of Basic Scientific Research,\u00c3\u00a2\u00e2\u0082\u00ac\u00c2\u009d Journal of Political Economy, 67, 297\u00c3\u00a2\u00e2\u0082\u00ac\u00e2\u0080\u009d306.",
        "Rosenberg, N. (1996): \u00c3\u00a2\u00e2\u0082\u00ac\u00c5\u0093Uncertainty and Technological Change,\u00c3\u00a2\u00e2\u0082\u00ac\u00c2\u009d in The Mosaic of Economic Growth, ed. by R. Landau, T. Taylor, and G. Wright. Stanford University Press.",
        "Serrano, C. J. (2006): \u00c3\u00a2\u00e2\u0082\u00ac\u00c5\u0093The Market for Intellectual Property: Evidence from the Transfer of Patents,\u00c3\u00a2\u00e2\u0082\u00ac\u00c2\u009d Ph.D. thesis, University of Minnesota.",
        "(2010): \u00c3\u00a2\u00e2\u0082\u00ac\u00c5\u0093The Dynamics of the Transfer and Renewal of Patents,\u00c3\u00a2\u00e2\u0082\u00ac\u00c2\u009d RAND Journal of Economics, 41, 686\u00c3\u00a2\u00e2\u0082\u00ac\u00e2\u0080\u009d708.",
        "Teece, D. J. (1986): \u00c3\u00a2\u00e2\u0082\u00ac\u00c5\u0093Profiting from technological innovation: Implications for integration, collaboration, licensing and public policy,\u00c3\u00a2\u00e2\u0082\u00ac\u00c2\u009d Research Policy, 15, 285\u00c3\u00a2\u00e2\u0082\u00ac\u00e2\u0080\u009d305.",
        "Trajtenberg, M. (1990): \u00c3\u00a2\u00e2\u0082\u00ac\u00c5\u0093A Penny for Your Quotes: Patent Citations and the Value of Innovations, \u00c3\u00a2\u00e2\u0082\u00ac\u00c2\u009d The Rand Journal of Economics, 21 (1), 172\u00c3\u00a2\u00e2\u0082\u00ac\u00e2\u0080\u009d187."
    ]
}